telebaka_voicebitch/bot.py
telebaka_voicebitch-0.1.dist-info/METADATA
telebaka_voicebitch-0.1.dist-info/RECORD
telebaka_voicebitch-0.1.dist-info/WHEEL
telebaka_voicebitch-0.1.dist-info/top_level.txt
